setup.py
cns/__init__.py
cns.recipe.maildrophost.egg-info/PKG-INFO
cns.recipe.maildrophost.egg-info/SOURCES.txt
cns.recipe.maildrophost.egg-info/dependency_links.txt
cns.recipe.maildrophost.egg-info/entry_points.txt
cns.recipe.maildrophost.egg-info/namespace_packages.txt
cns.recipe.maildrophost.egg-info/not-zip-safe
cns.recipe.maildrophost.egg-info/requires.txt
cns.recipe.maildrophost.egg-info/top_level.txt
cns/recipe/__init__.py
cns/recipe/maildrophost/__init__.py