Metadata-Version: 1.0
Name: cns.recipe.maildrophost
Version: 1.5.2
Summary: Recipe for installing MaildropHost
Home-page: http://svn.plone.org/svn/collective/cns.recipe.maildrophost
Author: Radim Novotny
Author-email: novotny.radim@gmail.com
License: GPL
Keywords: buildout recipe
Platform: UNKNOWN
Classifier: Framework :: Plone
Classifier: Framework :: Zope2
Classifier: Programming Language :: Python
Classifier: Topic :: Software Development :: Libraries :: Python Modules
